[{"id":0,"name":"Overall","rank":479900,"level":2009,"xp":104293147},{"id":1,"name":"Attack","rank":1183827,"level":82,"xp":2457752},{"id":2,"name":"Defence","rank":1037032,"level":82,"xp":2501447},{"id":3,"name":"Strength","rank":998169,"level":93,"xp":7898524},{"id":4,"name":"Hitpoints","rank":896916,"level":95,"xp":9466356},{"id":5,"name":"Ranged","rank":487167,"level":99,"xp":14971574},{"id":6,"name":"Prayer","rank":591197,"level":80,"xp":2151892},{"id":7,"name":"Magic","rank":1221639,"level":86,"xp":3867671},{"id":8,"name":"Cooking","rank":831185,"level":85,"xp":3263900},{"id":9,"name":"Woodcutting","rank":517494,"level":87,"xp":4109217},{"id":10,"name":"Fletching","rank":831685,"level":80,"xp":2075647},{"id":11,"name":"Fishing","rank":1050415,"level":75,"xp":1250313},{"id":12,"name":"Firemaking","rank":866930,"level":85,"xp":3258976},{"id":13,"name":"Crafting","rank":813776,"level":78,"xp":1637252},{"id":14,"name":"Smithing","rank":486792,"level":84,"xp":2974344},{"id":15,"name":"Mining","rank":967761,"level":76,"xp":1365512},{"id":16,"name":"Herblore","rank":882984,"level":72,"xp":918808},{"id":17,"name":"Agility","rank":923548,"level":74,"xp":1130004},{"id":18,"name":"Thieving","rank":693091,"level":77,"xp":1517094},{"id":19,"name":"Slayer","rank":976647,"level":77,"xp":1608924},{"id":20,"name":"Farming","rank":140171,"level":99,"xp":15580083},{"id":21,"name":"Runecraft","rank":376872,"level":80,"xp":2077877},{"id":22,"name":"Hunter","rank":591414,"level":80,"xp":1986157},{"id":23,"name":"Construction","rank":380724,"level":84,"xp":3188137},{"id":24,"name":"Sailing","rank":67145,"level":99,"xp":13035686}]