[{"id":0,"name":"Overall","rank":499021,"level":1988,"xp":98135401},{"id":1,"name":"Attack","rank":1204944,"level":82,"xp":2421988},{"id":2,"name":"Defence","rank":1025767,"level":82,"xp":2462288},{"id":3,"name":"Strength","rank":1053425,"level":92,"xp":6747586},{"id":4,"name":"Hitpoints","rank":910420,"level":95,"xp":9004606},{"id":5,"name":"Ranged","rank":477124,"level":99,"xp":14964582},{"id":6,"name":"Prayer","rank":577529,"level":80,"xp":2150672},{"id":7,"name":"Magic","rank":1227960,"level":86,"xp":3709332},{"id":8,"name":"Cooking","rank":1164354,"level":76,"xp":1339845},{"id":9,"name":"Woodcutting","rank":559117,"level":86,"xp":3638228},{"id":10,"name":"Fletching","rank":819050,"level":80,"xp":2074639},{"id":11,"name":"Fishing","rank":1042600,"level":75,"xp":1229529},{"id":12,"name":"Firemaking","rank":1146926,"level":78,"xp":1697850},{"id":13,"name":"Crafting","rank":799909,"level":78,"xp":1632052},{"id":14,"name":"Smithing","rank":475855,"level":84,"xp":2974168},{"id":15,"name":"Mining","rank":971036,"level":75,"xp":1309897},{"id":16,"name":"Herblore","rank":865106,"level":72,"xp":918176},{"id":17,"name":"Agility","rank":936769,"level":73,"xp":1096199},{"id":18,"name":"Thieving","rank":678216,"level":77,"xp":1516415},{"id":19,"name":"Slayer","rank":979636,"level":77,"xp":1531284},{"id":20,"name":"Farming","rank":136212,"level":99,"xp":15562605},{"id":21,"name":"Runecraft","rank":368082,"level":80,"xp":2077643},{"id":22,"name":"Hunter","rank":594504,"level":79,"xp":1860029},{"id":23,"name":"Construction","rank":372163,"level":84,"xp":3180245},{"id":24,"name":"Sailing","rank":55791,"level":99,"xp":13035543}]