[{"id":0,"name":"Overall","rank":504444,"level":1989,"xp":99339294},{"id":1,"name":"Attack","rank":1183160,"level":82,"xp":2443437},{"id":2,"name":"Defence","rank":1030012,"level":82,"xp":2483569},{"id":3,"name":"Strength","rank":1006941,"level":93,"xp":7532455},{"id":4,"name":"Hitpoints","rank":898031,"level":95,"xp":9306571},{"id":5,"name":"Ranged","rank":481847,"level":99,"xp":14964582},{"id":6,"name":"Prayer","rank":583152,"level":80,"xp":2151192},{"id":7,"name":"Magic","rank":1224451,"level":86,"xp":3782691},{"id":8,"name":"Cooking","rank":1171303,"level":76,"xp":1340295},{"id":9,"name":"Woodcutting","rank":563042,"level":86,"xp":3638228},{"id":10,"name":"Fletching","rank":824310,"level":80,"xp":2074639},{"id":11,"name":"Fishing","rank":1048816,"level":75,"xp":1229529},{"id":12,"name":"Firemaking","rank":1153744,"level":78,"xp":1697850},{"id":13,"name":"Crafting","rank":806140,"level":78,"xp":1632052},{"id":14,"name":"Smithing","rank":479825,"level":84,"xp":2974168},{"id":15,"name":"Mining","rank":979808,"level":75,"xp":1309897},{"id":16,"name":"Herblore","rank":872733,"level":72,"xp":918176},{"id":17,"name":"Agility","rank":944332,"level":73,"xp":1096199},{"id":18,"name":"Thieving","rank":683927,"level":77,"xp":1516415},{"id":19,"name":"Slayer","rank":986442,"level":77,"xp":1531284},{"id":20,"name":"Farming","rank":137945,"level":99,"xp":15562605},{"id":21,"name":"Runecraft","rank":371431,"level":80,"xp":2077643},{"id":22,"name":"Hunter","rank":599505,"level":79,"xp":1860029},{"id":23,"name":"Construction","rank":376009,"level":84,"xp":3180245},{"id":24,"name":"Sailing","rank":61068,"level":99,"xp":13035543}]