[{"id":0,"name":"Overall","rank":508071,"level":1970,"xp":94092817},{"id":1,"name":"Attack","rank":1268812,"level":80,"xp":2073943},{"id":2,"name":"Defence","rank":1008064,"level":82,"xp":2460471},{"id":3,"name":"Strength","rank":1087257,"level":91,"xp":6111973},{"id":4,"name":"Hitpoints","rank":917006,"level":94,"xp":8659406},{"id":5,"name":"Ranged","rank":470604,"level":99,"xp":14909710},{"id":6,"name":"Prayer","rank":561679,"level":80,"xp":2147097},{"id":7,"name":"Magic","rank":1212393,"level":86,"xp":3691173},{"id":8,"name":"Cooking","rank":1146328,"level":76,"xp":1339845},{"id":9,"name":"Woodcutting","rank":658670,"level":83,"xp":2775873},{"id":10,"name":"Fletching","rank":806959,"level":80,"xp":2074639},{"id":11,"name":"Fishing","rank":1026182,"level":75,"xp":1229529},{"id":12,"name":"Firemaking","rank":1259510,"level":75,"xp":1280629},{"id":13,"name":"Crafting","rank":805716,"level":77,"xp":1532292},{"id":14,"name":"Smithing","rank":465462,"level":84,"xp":2973943},{"id":15,"name":"Mining","rank":984888,"level":75,"xp":1245211},{"id":16,"name":"Herblore","rank":845776,"level":72,"xp":918112},{"id":17,"name":"Agility","rank":954259,"level":73,"xp":1045900},{"id":18,"name":"Thieving","rank":667461,"level":77,"xp":1515765},{"id":19,"name":"Slayer","rank":966036,"level":77,"xp":1515507},{"id":20,"name":"Farming","rank":133123,"level":99,"xp":15505947},{"id":21,"name":"Runecraft","rank":547450,"level":73,"xp":1047699},{"id":22,"name":"Hunter","rank":587269,"level":79,"xp":1831879},{"id":23,"name":"Construction","rank":362491,"level":84,"xp":3171259},{"id":24,"name":"Sailing","rank":35241,"level":99,"xp":13035015}]